classifier/__init__.py
classifier/core.py
classifier/registry.py
classifier/utils.py
classifier/description/__init__.py
classifier/description/ai_classifier.py
classifier/description/heuristic.py
classifier/evaluation/__init__.py
classifier/evaluation/ground_truth.py
classifier/predefine/__init__.py
classifier/predefine/javascript.py
classifier/predefine/php.py
classifier/predefine/python.py
tests/__init__.py
tests/example.py
tests/test_ai_classifier.py
tests/test_heuristic.py
tests/test_registry.py
repo_classifier-0.1.3.dist-info/LICENSE
repo_classifier-0.1.3.dist-info/METADATA
repo_classifier-0.1.3.dist-info/WHEEL
repo_classifier-0.1.3.dist-info/top_level.txt
repo_classifier-0.1.3.dist-info/RECORD
