Metadata-Version: 2.2
Name: repo_classifier
Version: 0.1.3
Summary: A library for classifying GitHub repositories
Home-page: https://github.com/YichaoXu/repo_classifier
Author: YichaoXU
Author-email: Yichao Xu <yxu166@jhu.edu>
License: MIT
Project-URL: Homepage, https://github.com/YichaoXu/repo_classifier
Project-URL: Documentation, https://github.com/YichaoXu/repo_classifier
Project-URL: Source, https://github.com/YichaoXu/repo_classifier
Classifier: Programming Language :: Python :: 3
Classifier: License :: OSI Approved :: MIT License
Classifier: Operating System :: OS Independent
Requires-Python: >=3.6
License-File: LICENSE
Requires-Dist: requests>=2.25.0
Provides-Extra: dev
Requires-Dist: pytest>=6.0.0; extra == "dev"
Requires-Dist: pytest-cov>=2.10.0; extra == "dev"
Requires-Dist: black>=20.8b1; extra == "dev"
Requires-Dist: isort>=5.0.0; extra == "dev"
Requires-Dist: mypy>=0.800; extra == "dev"
Dynamic: author
Dynamic: home-page
Dynamic: requires-python
